quality_master/classes/base_converter.py
quality_master/classes/code_quality_analyzer.py
quality_master/classes/code_quality_calculator.py
quality_master/classes/code_quality_reporter.py
quality_master/classes/file_detail_provider.py
quality_master/classes/html_converter.py
quality_master/classes/html_formatter.py
quality_master/classes/pylint_error_classification.py
quality_master/classes/pylint_runner.py
quality_master/classes/text_converter.py
quality_master/main.py
quality_master-23.11.30.dist-info/METADATA
quality_master-23.11.30.dist-info/WHEEL
quality_master-23.11.30.dist-info/entry_points.txt
quality_master-23.11.30.dist-info/RECORD
